MPpackage/Robot.cp311-win_amd64.pyd
MPpackage/__init__.py
MPpackage-0.1.dist-info/METADATA
MPpackage-0.1.dist-info/WHEEL
MPpackage-0.1.dist-info/top_level.txt
MPpackage-0.1.dist-info/RECORD
